eddytools/__init__.py
eddytools/__main__.py
eddytools/casenotions.py
eddytools/extraction.py
eddytools/schema.py
eddytools/events/__init__.py
eddytools/events/activity_identifier_discovery.py
eddytools/events/activity_identifier_feature_functions.py
eddytools/events/activity_identifier_predictors.py
eddytools/events/encoding.py
eddytools/resources/metamodel.sql
eddytools/resources/model_ev_disc.pkl
eddytools-0.3.data/scripts/eddytools
eddytools-0.3.dist-info/METADATA
eddytools-0.3.dist-info/RECORD
eddytools-0.3.dist-info/WHEEL
eddytools-0.3.dist-info/top_level.txt
