Metadata-Version: 2.1
Name: eddytools
Version: 0.3
Summary: Event Data Discovery tool
Home-page: https://github.com/edugonza/eddytools
Author: Eduardo Gonzalez Lopez de Murillas
Author-email: edu.gonza.lopez@gmail.com
License: MIT
Keywords: process mining events data extraction databases openslex
Platform: UNKNOWN
Classifier: Development Status :: 3 - Alpha
Classifier: License :: OSI Approved :: MIT License
Classifier: Programming Language :: Python :: 3.6
Requires-Python: >=3.6
Requires-Dist: sqlalchemy
Requires-Dist: psycopg2
Requires-Dist: setuptools
Requires-Dist: jellyfish
Requires-Dist: tqdm
Requires-Dist: numpy
Requires-Dist: networkx
Requires-Dist: pymssql
Requires-Dist: fcache
Requires-Dist: dateparser
Requires-Dist: scikit-learn
Requires-Dist: scipy
Requires-Dist: sqlitedict
Requires-Dist: pandas
Requires-Dist: flask
Requires-Dist: frozendict
Requires-Dist: pyyaml
Requires-Dist: xgboost
Requires-Dist: ciso8601
Requires-Dist: docopt
Requires-Dist: graphviz
